aiogmaps/__init__.py
aiogmaps/client.py
aiogmaps/directions.py
aiogmaps/distance_matrix.py
aiogmaps/elevation.py
aiogmaps/geocoding.py
aiogmaps/geolocation.py
aiogmaps/places.py
aiogmaps/roads.py
aiogmaps/timezone.py
aiogmaps-0.0.2.dist-info/LICENSE.txt
aiogmaps-0.0.2.dist-info/METADATA
aiogmaps-0.0.2.dist-info/WHEEL
aiogmaps-0.0.2.dist-info/top_level.txt
aiogmaps-0.0.2.dist-info/RECORD
