Metadata-Version: 2.1
Name: aiogmaps
Version: 0.0.2
Summary: Asyncio client library for Google Maps API Web Services
Home-page: https://github.com/hzlmn/aiogmaps
Author: Oleh Kuchuk
Author-email: kuchuklehjs@gmail.com
License: MIT
Keywords: asyncio,aiohttp
Platform: UNKNOWN
Classifier: Intended Audience :: Developers
Classifier: License :: OSI Approved :: MIT License
Classifier: Programming Language :: Python
Classifier: Programming Language :: Python :: 3.6
Requires-Dist: aiohttp (>=2.3.5)
Requires-Dist: googlemaps (>=3.0.0)
